django_signposting/__init__.py
django_signposting/middleware.py
django_signposting/sparql.py
django_signposting/utils.py
django_signposting-0.11.0.dist-info/LICENSE
django_signposting-0.11.0.dist-info/METADATA
django_signposting-0.11.0.dist-info/WHEEL
django_signposting-0.11.0.dist-info/top_level.txt
django_signposting-0.11.0.dist-info/RECORD
