Metadata-Version: 2.1
Name: django_signposting
Version: 0.11.0
Summary: Add FAIR signpostings to response headers in Django
Author-email: Daniel Bauer <github@dbauer.me>
License: MIT License
Project-URL: Homepage, https://github.com/dnlbauer/django-signposting
Requires-Python: >=3.10
License-File: LICENSE
Requires-Dist: beautifulsoup4>=4.12.3
Requires-Dist: django>=3.0
Requires-Dist: signposting>=0.9.9
Requires-Dist: rdflib>=7.1.1
Provides-Extra: dev
Requires-Dist: pytest; extra == "dev"
